{
    "os": "Linux-5.4.0-131-generic-x86_64-with-glibc2.31",
    "python": "3.9.15",
    "heartbeatAt": "2023-05-01T20:57:02.094027",
    "startedAt": "2023-05-01T20:57:01.274740",
    "docker": null,
    "cuda": null,
    "args": [
        "--name",
        "controled"
    ],
    "state": "running",
    "program": "/home/mila/g/gagnonju/Marg-Li-CoT/trl/scratchpad/gpt2-sentiment-control.py",
    "codePath": "trl/scratchpad/gpt2-sentiment-control.py",
    "git": {
        "remote": "git@github.com:JulesGM/Marg-Li-CoT.git",
        "commit": "bab88d20ade8d2573a9c3970bfc7a818e251a0e2"
    },
    "email": "jules.gagnonm.alt@gmail.com",
    "root": "/home/mila/g/gagnonju/Marg-Li-CoT",
    "host": "cn-d001",
    "username": "gagnonju",
    "executable": "/home/mila/g/gagnonju/.main/bin/python",
    "cpu_count": 128,
    "cpu_count_logical": 128,
    "cpu_freq": {
        "current": 3182.2298749999995,
        "min": 1500.0,
        "max": 2250.0
    },
    "cpu_freq_per_core": [
        {
            "current": 3360.05,
            "min": 1500.0,
            "max": 2250.0
        },
        {
            "current": 3357.372,
            "min": 1500.0,
            "max": 2250.0
        },
        {
            "current": 1577.901,
            "min": 1500.0,
            "max": 2250.0
        },
        {
            "current": 1569.735,
            "min": 1500.0,
            "max": 2250.0
        },
        {
            "current": 2973.703,
            "min": 1500.0,
            "max": 2250.0
        },
        {
            "current": 2965.043,
            "min": 1500.0,
            "max": 2250.0
        },
        {
            "current": 3354.651,
            "min": 1500.0,
            "max": 2250.0
        },
        {
            "current": 2960.926,
            "min": 1500.0,
            "max": 2250.0
        },
        {
            "current": 3002.623,
            "min": 1500.0,
            "max": 2250.0
        },
        {
            "current": 2949.763,
            "min": 1500.0,
            "max": 2250.0
        },
        {
            "current": 3360.797,
            "min": 1500.0,
            "max": 2250.0
        },
        {
            "current": 2997.284,
            "min": 1500.0,
            "max": 2250.0
        },
        {
            "current": 3358.303,
            "min": 1500.0,
            "max": 2250.0
        },
        {
            "current": 3357.224,
            "min": 1500.0,
            "max": 2250.0
        },
        {
            "current": 3009.573,
            "min": 1500.0,
            "max": 2250.0
        },
        {
            "current": 2097.96,
            "min": 1500.0,
            "max": 2250.0
        },
        {
            "current": 3022.818,
            "min": 1500.0,
            "max": 2250.0
        },
        {
            "current": 2957.021,
            "min": 1500.0,
            "max": 2250.0
        },
        {
            "current": 1874.605,
            "min": 1500.0,
            "max": 2250.0
        },
        {
            "current": 2991.062,
            "min": 1500.0,
            "max": 2250.0
        },
        {
            "current": 2215.314,
            "min": 1500.0,
            "max": 2250.0
        },
        {
            "current": 2932.054,
            "min": 1500.0,
            "max": 2250.0
        },
        {
            "current": 3357.497,
            "min": 1500.0,
            "max": 2250.0
        },
        {
            "current": 3365.817,
            "min": 1500.0,
            "max": 2250.0
        },
        {
            "current": 3356.001,
            "min": 1500.0,
            "max": 2250.0
        },
        {
            "current": 3355.452,
            "min": 1500.0,
            "max": 2250.0
        },
        {
            "current": 3355.143,
            "min": 1500.0,
            "max": 2250.0
        },
        {
            "current": 3354.811,
            "min": 1500.0,
            "max": 2250.0
        },
        {
            "current": 2968.445,
            "min": 1500.0,
            "max": 2250.0
        },
        {
            "current": 3055.452,
            "min": 1500.0,
            "max": 2250.0
        },
        {
            "current": 3025.556,
            "min": 1500.0,
            "max": 2250.0
        },
        {
            "current": 3380.243,
            "min": 1500.0,
            "max": 2250.0
        },
        {
            "current": 2353.692,
            "min": 1500.0,
            "max": 2250.0
        },
        {
            "current": 2973.319,
            "min": 1500.0,
            "max": 2250.0
        },
        {
            "current": 3353.384,
            "min": 1500.0,
            "max": 2250.0
        },
        {
            "current": 2195.981,
            "min": 1500.0,
            "max": 2250.0
        },
        {
            "current": 3043.226,
            "min": 1500.0,
            "max": 2250.0
        },
        {
            "current": 2228.828,
            "min": 1500.0,
            "max": 2250.0
        },
        {
            "current": 2107.304,
            "min": 1500.0,
            "max": 2250.0
        },
        {
            "current": 2930.67,
            "min": 1500.0,
            "max": 2250.0
        },
        {
            "current": 2361.243,
            "min": 1500.0,
            "max": 2250.0
        },
        {
            "current": 2292.736,
            "min": 1500.0,
            "max": 2250.0
        },
        {
            "current": 3024.951,
            "min": 1500.0,
            "max": 2250.0
        },
        {
            "current": 2993.348,
            "min": 1500.0,
            "max": 2250.0
        },
        {
            "current": 2293.501,
            "min": 1500.0,
            "max": 2250.0
        },
        {
            "current": 2545.077,
            "min": 1500.0,
            "max": 2250.0
        },
        {
            "current": 2131.151,
            "min": 1500.0,
            "max": 2250.0
        },
        {
            "current": 1679.32,
            "min": 1500.0,
            "max": 2250.0
        },
        {
            "current": 1598.316,
            "min": 1500.0,
            "max": 2250.0
        },
        {
            "current": 3000.967,
            "min": 1500.0,
            "max": 2250.0
        },
        {
            "current": 3324.041,
            "min": 1500.0,
            "max": 2250.0
        },
        {
            "current": 2569.91,
            "min": 1500.0,
            "max": 2250.0
        },
        {
            "current": 3355.054,
            "min": 1500.0,
            "max": 2250.0
        },
        {
            "current": 3346.25,
            "min": 1500.0,
            "max": 2250.0
        },
        {
            "current": 3335.036,
            "min": 1500.0,
            "max": 2250.0
        },
        {
            "current": 2969.386,
            "min": 1500.0,
            "max": 2250.0
        },
        {
            "current": 2287.313,
            "min": 1500.0,
            "max": 2250.0
        },
        {
            "current": 2790.159,
            "min": 1500.0,
            "max": 2250.0
        },
        {
            "current": 2533.12,
            "min": 1500.0,
            "max": 2250.0
        },
        {
            "current": 2143.268,
            "min": 1500.0,
            "max": 2250.0
        },
        {
            "current": 2127.035,
            "min": 1500.0,
            "max": 2250.0
        },
        {
            "current": 3286.895,
            "min": 1500.0,
            "max": 2250.0
        },
        {
            "current": 2474.8,
            "min": 1500.0,
            "max": 2250.0
        },
        {
            "current": 2472.328,
            "min": 1500.0,
            "max": 2250.0
        },
        {
            "current": 3390.722,
            "min": 1500.0,
            "max": 2250.0
        },
        {
            "current": 3390.568,
            "min": 1500.0,
            "max": 2250.0
        },
        {
            "current": 3389.47,
            "min": 1500.0,
            "max": 2250.0
        },
        {
            "current": 3392.495,
            "min": 1500.0,
            "max": 2250.0
        },
        {
            "current": 2424.235,
            "min": 1500.0,
            "max": 2250.0
        },
        {
            "current": 2398.633,
            "min": 1500.0,
            "max": 2250.0
        },
        {
            "current": 2382.548,
            "min": 1500.0,
            "max": 2250.0
        },
        {
            "current": 2386.908,
            "min": 1500.0,
            "max": 2250.0
        },
        {
            "current": 3385.696,
            "min": 1500.0,
            "max": 2250.0
        },
        {
            "current": 2439.916,
            "min": 1500.0,
            "max": 2250.0
        },
        {
            "current": 2226.754,
            "min": 1500.0,
            "max": 2250.0
        },
        {
            "current": 2398.68,
            "min": 1500.0,
            "max": 2250.0
        },
        {
            "current": 2460.874,
            "min": 1500.0,
            "max": 2250.0
        },
        {
            "current": 1748.314,
            "min": 1500.0,
            "max": 2250.0
        },
        {
            "current": 2397.538,
            "min": 1500.0,
            "max": 2250.0
        },
        {
            "current": 2382.395,
            "min": 1500.0,
            "max": 2250.0
        },
        {
            "current": 3381.167,
            "min": 1500.0,
            "max": 2250.0
        },
        {
            "current": 3384.799,
            "min": 1500.0,
            "max": 2250.0
        },
        {
            "current": 2456.239,
            "min": 1500.0,
            "max": 2250.0
        },
        {
            "current": 3385.662,
            "min": 1500.0,
            "max": 2250.0
        },
        {
            "current": 3385.531,
            "min": 1500.0,
            "max": 2250.0
        },
        {
            "current": 3385.528,
            "min": 1500.0,
            "max": 2250.0
        },
        {
            "current": 3390.789,
            "min": 1500.0,
            "max": 2250.0
        },
        {
            "current": 3383.991,
            "min": 1500.0,
            "max": 2250.0
        },
        {
            "current": 3393.263,
            "min": 1500.0,
            "max": 2250.0
        },
        {
            "current": 2353.72,
            "min": 1500.0,
            "max": 2250.0
        },
        {
            "current": 2340.326,
            "min": 1500.0,
            "max": 2250.0
        },
        {
            "current": 3385.376,
            "min": 1500.0,
            "max": 2250.0
        },
        {
            "current": 3389.785,
            "min": 1500.0,
            "max": 2250.0
        },
        {
            "current": 2328.994,
            "min": 1500.0,
            "max": 2250.0
        },
        {
            "current": 2387.244,
            "min": 1500.0,
            "max": 2250.0
        },
        {
            "current": 2336.464,
            "min": 1500.0,
            "max": 2250.0
        },
        {
            "current": 3384.616,
            "min": 1500.0,
            "max": 2250.0
        },
        {
            "current": 2332.985,
            "min": 1500.0,
            "max": 2250.0
        },
        {
            "current": 2322.083,
            "min": 1500.0,
            "max": 2250.0
        },
        {
            "current": 2445.284,
            "min": 1500.0,
            "max": 2250.0
        },
        {
            "current": 2456.449,
            "min": 1500.0,
            "max": 2250.0
        },
        {
            "current": 2544.143,
            "min": 1500.0,
            "max": 2250.0
        },
        {
            "current": 2509.121,
            "min": 1500.0,
            "max": 2250.0
        },
        {
            "current": 2490.637,
            "min": 1500.0,
            "max": 2250.0
        },
        {
            "current": 2480.39,
            "min": 1500.0,
            "max": 2250.0
        },
        {
            "current": 2495.945,
            "min": 1500.0,
            "max": 2250.0
        },
        {
            "current": 2503.092,
            "min": 1500.0,
            "max": 2250.0
        },
        {
            "current": 2505.379,
            "min": 1500.0,
            "max": 2250.0
        },
        {
            "current": 2476.219,
            "min": 1500.0,
            "max": 2250.0
        },
        {
            "current": 2497.635,
            "min": 1500.0,
            "max": 2250.0
        },
        {
            "current": 2504.017,
            "min": 1500.0,
            "max": 2250.0
        },
        {
            "current": 2506.413,
            "min": 1500.0,
            "max": 2250.0
        },
        {
            "current": 2431.341,
            "min": 1500.0,
            "max": 2250.0
        },
        {
            "current": 3389.731,
            "min": 1500.0,
            "max": 2250.0
        },
        {
            "current": 3380.141,
            "min": 1500.0,
            "max": 2250.0
        },
        {
            "current": 2436.211,
            "min": 1500.0,
            "max": 2250.0
        },
        {
            "current": 3385.105,
            "min": 1500.0,
            "max": 2250.0
        },
        {
            "current": 2344.573,
            "min": 1500.0,
            "max": 2250.0
        },
        {
            "current": 3391.052,
            "min": 1500.0,
            "max": 2250.0
        },
        {
            "current": 3398.116,
            "min": 1500.0,
            "max": 2250.0
        },
        {
            "current": 2436.223,
            "min": 1500.0,
            "max": 2250.0
        },
        {
            "current": 3382.889,
            "min": 1500.0,
            "max": 2250.0
        },
        {
            "current": 2337.056,
            "min": 1500.0,
            "max": 2250.0
        },
        {
            "current": 3390.427,
            "min": 1500.0,
            "max": 2250.0
        },
        {
            "current": 3393.29,
            "min": 1500.0,
            "max": 2250.0
        },
        {
            "current": 3403.611,
            "min": 1500.0,
            "max": 2250.0
        },
        {
            "current": 3389.694,
            "min": 1500.0,
            "max": 2250.0
        },
        {
            "current": 3389.137,
            "min": 1500.0,
            "max": 2250.0
        }
    ],
    "disk": {
        "total": 1757.7545127868652,
        "used": 98.92605972290039
    },
    "gpu": "NVIDIA A100-SXM4-40GB",
    "gpu_count": 1,
    "gpu_devices": [
        {
            "name": "NVIDIA A100-SXM4-40GB",
            "memory_total": 42505273344
        }
    ],
    "memory": {
        "total": 1007.7281913757324
    }
}
